zmqflp/__init__.py
zmqflp/zmqflp_api.py
zmqflp/zmqflp_client.py
zmqflp/zmqflp_managed_client.py
zmqflp/zmqflp_server.py
zmqflp/zmqflp_tests.py
zmqflp-0.8.3.dist-info/METADATA
zmqflp-0.8.3.dist-info/RECORD
zmqflp-0.8.3.dist-info/WHEEL
zmqflp-0.8.3.dist-info/top_level.txt
