Metadata-Version: 2.1
Name: zmqflp
Version: 0.8.3
Summary: PyZMQ server/client implementing asyncio freelance protocol based on Min RK's starter code
Home-page: https://github.com/curtywang/zmqflp
Author: Curtis Wang
Author-email: ycwang@u.northwestern.edu
License: UNKNOWN
Platform: UNKNOWN
Classifier: Programming Language :: Python :: 3
Classifier: License :: OSI Approved :: Mozilla Public License 2.0 (MPL 2.0)
Classifier: Operating System :: OS Independent
Classifier: Topic :: Software Development :: Libraries
Classifier: Topic :: System :: Networking
Requires-Dist: pyzmq
Requires-Dist: cbor2
